
{"items":[{"name":"Plugs","href":"plugs.html","topicHref":"plugs.html"},{"name":"Cosmos.Asm.Build","href":"asm-build.md","topicHref":"asm-build.md"},{"name":"Cosmos.ilc.Build","href":"ilc-build.md","topicHref":"ilc-build.md"},{"name":"Cosmos.Patcher.Build","href":"patcher-build.md","topicHref":"patcher-build.md"},{"name":"Kernel Compilation Steps","href":"kernel-compilation-steps.md","topicHref":"kernel-compilation-steps.md"},{"name":"Garbage Collector","href":"garbage-collector.html","topicHref":"garbage-collector.html"},{"name":"Testing","href":"testing.html","topicHref":"testing.html"},{"name":"Kernel Project Layout","href":"kernel-project-layout.html","topicHref":"kernel-project-layout.html"}],"pdf":false}
